pytorch_numba_extension_jit/__init__.py
pytorch_numba_extension_jit/_as_dtype.py
pytorch_numba_extension_jit/_codegen.py
pytorch_numba_extension_jit/_compiler.py
pytorch_numba_extension_jit/_torchlib_wrapper.py
pytorch_numba_extension_jit/_typehint_interface.py
pytorch_numba_extension_jit/py.typed
pytorch_numba_extension_jit-0.1.6.dist-info/METADATA
pytorch_numba_extension_jit-0.1.6.dist-info/WHEEL
pytorch_numba_extension_jit-0.1.6.dist-info/licenses/LICENSE
pytorch_numba_extension_jit-0.1.6.dist-info/RECORD
