Metadata-Version: 2.4
Name: pytorch-numba-extension-jit
Version: 0.1.6
Summary: Generate PyTorch Custom Operators from Numba-CUDA kernels
Author-email: Peter Adema <p.j.adema@uva.nl>
License-Expression: MIT
License-File: LICENSE
Requires-Python: >=3.10
Requires-Dist: cuda-bindings>=11; sys_platform != 'darwin'
Requires-Dist: numba-cuda<0.15.0,>=0.9.0; sys_platform == 'darwin'
Requires-Dist: numba-cuda>=0.9.0; sys_platform != 'darwin'
Requires-Dist: torch>=2.6.0
Requires-Dist: uuid>=1.30
